{
  "_class": "shapeGroup",
  "booleanOperation": -1,
  "clippingMaskMode": 0,
  "do_objectID": "FCB80B44-B4C0-4264-A9B6-119CAA86B023",
  "exportOptions": {
    "_class": "exportOptions",
    "exportFormats": [
    ],
    "includedLayerIds": [
    ],
    "layerOptions": 0,
    "shouldTrim": false
  },
  "frame": {
    "_class": "rect",
    "constrainProportions": true,
    "height": 38.67999999999998,
    "width": 198.88,
    "x": 81.00000000000004,
    "y": 294
  },
  "groupLayout": {
    "_class": "MSImmutableFreeformGroupLayout"
  },
  "hasClickThrough": false,
  "hasClippingMask": false,
  "isFixedToViewport": false,
  "isFlippedHorizontal": false,
  "isFlippedVertical": false,
  "isLocked": false,
  "isVisible": true,
  "layerListExpandedType": 1,
  "layers": [
    {
      "class": "shapePath",
      "id": "6E0E41F0-5432-4682-844B-BAE61BC85396"
    },
    {
      "class": "shapePath",
      "id": "89D3B4E3-EB1A-40D2-B4B6-34E61E3F1DEC"
    },
    {
      "class": "shapePath",
      "id": "1DADB0A7-FDD0-4F10-9BCE-FAD88D2A96D9"
    },
    {
      "class": "shapePath",
      "id": "24CEF5BB-D427-40D4-B0DA-72ED08A555B1"
    },
    {
      "class": "shapePath",
      "id": "7CBB8A72-1F8A-444F-8220-A9B451222C68"
    },
    {
      "class": "shapePath",
      "id": "44B2DEB6-83AF-4659-9FCA-14AABFE1E649"
    },
    {
      "class": "shapePath",
      "id": "63E800FD-5AA9-41EC-B423-3F96AC275625"
    },
    {
      "class": "shapePath",
      "id": "234DE372-37C3-461C-9E3A-1778BB7D4A32"
    },
    {
      "class": "shapePath",
      "id": "241D8DF9-7F4C-4057-86DE-B52075C1496C"
    },
    {
      "class": "shapePath",
      "id": "B5B8BAEF-607A-4226-8641-3B52012DAC8B"
    },
    {
      "class": "shapePath",
      "id": "6AD323EE-C557-49A3-ADB6-D2D4258D6848"
    },
    {
      "class": "shapePath",
      "id": "C10FDC8A-7E18-42E9-9B2E-1F014126CBE6"
    },
    {
      "class": "shapePath",
      "id": "BFCE6A1B-24C0-4570-9DC8-21ACA8A9CD3A"
    },
    {
      "class": "shapePath",
      "id": "CC6D6E7F-4E5B-4B21-B93D-EF2E2886B70D"
    },
    {
      "class": "shapePath",
      "id": "14389897-E038-49DD-ADF3-D2E8D4B5B15F"
    },
    {
      "class": "shapePath",
      "id": "BACA6D6B-E0BD-4CCD-B328-D709268340A9"
    }
  ],
  "name": "懂文化传媒",
  "nameIsFixed": false,
  "resizingConstraint": 63,
  "resizingType": 0,
  "rotation": 0,
  "shouldBreakMaskChain": false,
  "style": {
    "_class": "style",
    "endMarkerType": 0,
    "fills": [
      {
        "_class": "fill",
        "color": {
          "_class": "color",
          "alpha": 1,
          "blue": 0.3843137254901961,
          "green": 0.5333333333333333,
          "red": 0.6392156862745098
        },
        "fillType": 1,
        "gradient": {
          "_class": "gradient",
          "elipseLength": 0,
          "from": "{0.5, 0}",
          "gradientType": 0,
          "stops": [
            {
              "_class": "gradientStop",
              "color": {
                "_class": "color",
                "alpha": 1,
                "blue": 0.5529411764705883,
                "green": 0.7254901960784313,
                "red": 0.8156862745098039
              },
              "position": 0
            },
            {
              "_class": "gradientStop",
              "color": {
                "_class": "color",
                "alpha": 1,
                "blue": 0.4235294117647059,
                "green": 0.5882352941176471,
                "red": 0.7058823529411765
              },
              "position": 1
            }
          ],
          "to": "{0.5, 1}"
        },
        "isEnabled": true,
        "noiseIndex": 0,
        "noiseIntensity": 0,
        "patternFillType": 1,
        "patternTileScale": 1
      }
    ],
    "miterLimit": 10,
    "startMarkerType": 0,
    "windingRule": 0
  },
  "windingRule": 0
}